Metadata-Version: 2.4
Name: iflow-mcp_mcp-databricks-server
Version: 0.1.0
Summary: A Model Context Protocol server that connects to Databricks API
Requires-Python: >=3.7
Requires-Dist: databricks-sql-connector>=2.4.0
Requires-Dist: fastapi>=0.95.0
Requires-Dist: mcp>=0.1.0
Requires-Dist: packaging>=23.0
Requires-Dist: pyarrow>=14.0.1
Requires-Dist: pydantic>=2.0.0
Requires-Dist: python-dotenv>=1.0.0
Requires-Dist: requests>=2.31.0
Requires-Dist: uvicorn>=0.22.0
